ScipyCookbookFix1/README.md
ScipyCookbookFix1/__init__.py
ScipyCookbookFix1/__main__.py
ScipyCookbookFix1/file.epub
ScipyCookbookFix1/index.html
ScipyCookbookFix1/css/__init__.py
ScipyCookbookFix1/css/annotations.css
ScipyCookbookFix1/css/main.css
ScipyCookbookFix1/css/normalize.css
ScipyCookbookFix1/css/popup.css
ScipyCookbookFix1/font/__init__.py
ScipyCookbookFix1/font/fontello.eot
ScipyCookbookFix1/font/fontello.svg
ScipyCookbookFix1/font/fontello.ttf
ScipyCookbookFix1/font/fontello.woff
ScipyCookbookFix1/img/__init__.py
ScipyCookbookFix1/img/annotator-glyph-sprite.png
ScipyCookbookFix1/img/annotator-icon-sprite.png
ScipyCookbookFix1/img/apple-touch-icon.png
ScipyCookbookFix1/img/cancelfullscreen.png
ScipyCookbookFix1/img/close.png
ScipyCookbookFix1/img/fullscreen.png
ScipyCookbookFix1/img/loader.gif
ScipyCookbookFix1/img/menu-icon.png
ScipyCookbookFix1/img/save.png
ScipyCookbookFix1/img/saved.png
ScipyCookbookFix1/img/settings-s.png
ScipyCookbookFix1/img/settings.png
ScipyCookbookFix1/img/star.png
ScipyCookbookFix1/js/__init__.py
ScipyCookbookFix1/js/epub.js
ScipyCookbookFix1/js/epub.min.js
ScipyCookbookFix1/js/epub.min.map
ScipyCookbookFix1/js/hooks.min.js
ScipyCookbookFix1/js/hooks.min.map
ScipyCookbookFix1/js/reader.js
ScipyCookbookFix1/js/reader.js.map
ScipyCookbookFix1/js/reader.min.js
ScipyCookbookFix1/js/reader.min.map
ScipyCookbookFix1/js/hooks/__init__.py
ScipyCookbookFix1/js/hooks/extensions/__init__.py
ScipyCookbookFix1/js/hooks/extensions/highlight.js
ScipyCookbookFix1/js/libs/__init__.py
ScipyCookbookFix1/js/libs/jquery.min.js
ScipyCookbookFix1/js/libs/localforage.min.js
ScipyCookbookFix1/js/libs/screenfull.js
ScipyCookbookFix1/js/libs/screenfull.min.js
ScipyCookbookFix1/js/libs/zip.min.js
ScipyCookbookFix1/js/plugins/__init__.py
ScipyCookbookFix1/js/plugins/hypothesis.js
ScipyCookbookFix1/js/plugins/search.js
scipy_cookbook_fix1-2024.3.2.0.dist-info/METADATA
scipy_cookbook_fix1-2024.3.2.0.dist-info/WHEEL
scipy_cookbook_fix1-2024.3.2.0.dist-info/entry_points.txt
scipy_cookbook_fix1-2024.3.2.0.dist-info/top_level.txt
scipy_cookbook_fix1-2024.3.2.0.dist-info/RECORD
